{
  "name": "apt-get",
  "description": "command-line tool for handling packages???",
  "subcommands": [
    {
      "name": "update",
      "description": "Update all packages"
    },
    {
      "name": "upgrade",
      "description": "Install the newest versions of all packages currently installed on the system"
    },
    {
      "name": "dist-upgrade",
      "description": "Same as upgrade, but also handles changing dependencies with new versions of packages"
    },
    {
      "name": "dselect-upgrade",
      "description": "Follows the changes made by dselect(1) to the Status field of available packages"
    },
    {
      "name": "install",
      "description": "Install package(s)"
    },
    {
      "name": "remove",
      "description": "Remove package(s)"
    },
    {
      "name": "purge",
      "description": "Same as remove, but also deletes configuration files"
    },
    {
      "name": "source",
      "description": "Fetch source packages",
      "options": [
        {
          "name": "--compile",
          "description": "The package will be compiled to a binary .deb"
        },
        {
          "name": "--download-only",
          "description": "The source package will not be unpacked"
        }
      ]
    },
    {
      "name": "build-dep",
      "description": "Install/remove packages in an attempt to satisfy the build dependencies for a source package"
    },
    {
      "name": "check",
      "description": "Updates the package cache and checks for broken dependencies"
    },
    {
      "name": "download",
      "description": "Download the given binary package into the current directory"
    },
    {
      "name": "clean",
      "description": "Clears out the local repository of retrieved package files"
    },
    {
      "name": "autoclean",
      "alias": "auto-clean",
      "description": "Same as clean, but only removes package files that can no longer be downloaded"
    },
    {
      "name": "autoremove",
      "alias": "auto-remove",
      "description": "Remove packages that were automatically installed to satisfy dependencies for other packages and are no longer needed"
    },
    {
      "name": "changelog",
      "description": "Displays the changelog of a package"
    },
    {
      "name": "indextargets",
      "description": "Displays a listing of information about all data files (aka index targets) apt-get update would download"
    }
  ],
  "options": [
    {
      "name": "--no-install-recommends",
      "description": "Do not consider recommended packages as a dependency for installing"
    },
    {
      "name": "--install-suggests",
      "description": "Consider suggested packages as a dependency for installing"
    },
    {
      "name": ["-d", "--download-only"],
      "description": "Package files are only retrieved, not unpacked or installed"
    },
    {
      "name": ["-f", "--fix-broken"],
      "description": "Attempt to correct a system with broken dependencies in place"
    },
    {
      "name": ["-m", "--ignore-missing", "--fix-missing"],
      "description": "Ignore missing packages"
    },
    {
      "name": "--no-download",
      "description": "Disables downloading of packages"
    },
    {
      "name": ["-q", "--quiet"],
      "description": "Produces output suitable for logging, omitting progress indicators"
    },
    {
      "name": [
        "-s",
        "--simulate",
        "--just-print",
        "--dry-run",
        "--recon",
        "--no-act"
      ],
      "description": "Perform a simulation of events that would occur based on the current system state but do not actually change the system"
    },
    {
      "name": ["-y", "--yes", "--assume-yes"],
      "description": "Automatic yes to all prompts"
    },
    {
      "name": "--assume-no",
      "description": "Automatic no to all prompts"
    },
    {
      "name": ["-u", "--show-upgraded"],
      "description": "Show upgraded packages"
    },
    {
      "name": ["-V", "--verbose-versions"],
      "description": "Show full versions for upgraded and installed packages"
    },
    {
      "name": ["-a", "--host-architecture"],
      "description": "Controls the architecture packages are built for by apt-get source --compile and how cross-builddependencies are satisfied"
    },
    {
      "name": "",
      "description": ""
    },
    {
      "name": "",
      "description": ""
    },
    {
      "name": "",
      "description": ""
    },
    {
      "name": "",
      "description": ""
    },
    {
      "name": "",
      "description": ""
    },
    {
      "name": ["-h", "--help"],
      "description": "Print help message and exit",
      "isPersistent": true,
      "priority": 40
    },
    {
      "name": ["-v", "--version"],
      "description": "Print version information and exit",
      "isPersistent": true,
      "priority": 40
    }
  ]
}
